hello.py
test_uv-0.1.0.dist-info/METADATA
test_uv-0.1.0.dist-info/WHEEL
test_uv-0.1.0.dist-info/top_level.txt
test_uv-0.1.0.dist-info/RECORD
